CHANGELOG.md
LICENSE.md
README.md
metastore/__init__.py
metastore/package.py
metastore/utils.py
metastore-1.0.0.dev21.dist-info/LICENSE.md
metastore-1.0.0.dev21.dist-info/METADATA
metastore-1.0.0.dev21.dist-info/WHEEL
metastore-1.0.0.dev21.dist-info/top_level.txt
metastore-1.0.0.dev21.dist-info/RECORD
