Metadata-Version: 2.1
Name: metastore
Version: 1.0.0.dev21
Summary: Metastore Python SDK. Feature store and data catalog for machine learning.
Home-page: https://metastore.readthedocs.io
Author: Metastore Developers
Author-email: metastoredevelopers@gmail.com
License: BSD-3-Clause
Download-URL: https://pypi.org/project/metastore
Project-URL: Code, https://github.com/metastore-developers/metastore
Project-URL: Issue tracker, https://github.com/metastore-developers/metastore/issues
Platform: UNKNOWN
Classifier: Programming Language :: Python
Classifier: Programming Language :: Python :: 3
Classifier: Programming Language :: Python :: 3.7
Classifier: License :: OSI Approved :: BSD License
Requires-Python: >=3.7.0
License-File: LICENSE.md
Requires-Dist: dask (>=2021.10.0)
Provides-Extra: development
Requires-Dist: setuptools (>=58.2.0) ; extra == 'development'
Requires-Dist: wheel (>=0.37.0) ; extra == 'development'
Requires-Dist: autopep8 (>=1.6.0) ; extra == 'development'
Requires-Dist: pylint (>=2.12.0) ; extra == 'development'
Requires-Dist: pytest (>=6.2.0) ; extra == 'development'
Requires-Dist: pytest-cov (>=3.0.0) ; extra == 'development'
Requires-Dist: sphinx (>=4.3.0) ; extra == 'development'
Requires-Dist: myst-parser (>=0.15.0) ; extra == 'development'
Requires-Dist: pydata-sphinx-theme (>=0.7.0) ; extra == 'development'
Requires-Dist: twine (>=3.7.0) ; extra == 'development'
